{
  "updated": "2026-06-14 08:38",
  "alert": "",
  "notes": [
    "ℹ️ Оновлення в приміському русі через ремонтні роботи інфраструктури та покращення низки маршрутів. ⏱️ З 13 по 20 червня поїзд №6334 Помічна – Знамʼянка змінить графік на 16:05 - 19:16 (замість 15:25 - 18:47). З 15 червня змінюємо розклад в напрямку Берестина. Низка поїздів відправлятиметься з почат"
  ],
  "cancellations": {},
  "changes": {
    "6693": {
      "status": "changed",
      "note": "Зміни в розкладі",
      "source": "ℹ️ Оновлення в приміському русі через ремонтні роботи інфраструктури та покращення низки маршрутів. "
    }
  }
}